nwc/__init__.py
nwc-0.0.0.dist-info/METADATA
nwc-0.0.0.dist-info/WHEEL
nwc-0.0.0.dist-info/top_level.txt
nwc-0.0.0.dist-info/RECORD
