Metadata-Version: 2.1
Name: nwc
Version: 0.0.0
Summary: Coming soon
Author-email: Yuki Kishimoto <yukikishimoto@protonmail.com>
